{
  "updated_at": "2026-07-16T13:43:23.053191",
  "news": [
    {
      "headline": "百萬年海洋故事藏在化石裡嘉市立博物館《未來海洋：化石裡的生態暗號》邀民眾一探究竟",
      "source": "嘉義市政府/文化局/觀光新聞處",
      "link": "https://www.chiayi.gov.tw/News_Content.aspx?n=455&s=946085",
      "date": "2026/07/16",
      "query": "市府新聞"
    },
    {
      "headline": "首次抗高溫演練強化嘉園韌性",
      "source": "嘉義市政府/嘉義市政府環境保護局/綜合計畫科",
      "link": "https://www.chiayi.gov.tw/News_Content.aspx?n=455&s=945758",
      "date": "2026/07/16",
      "query": "市府新聞"
    },
    {
      "headline": "嘉義市翻轉靜態閱讀！公共圖書館打造親子五感閱讀森林",
      "source": "嘉義市政府/文化局/觀光新聞處",
      "link": "https://www.chiayi.gov.tw/News_Content.aspx?n=455&s=946050",
      "date": "2026/07/16",
      "query": "市府新聞"
    },
    {
      "headline": "嘉義市政府115年7月份公報",
      "source": "嘉義市政府/行政處",
      "link": "https://www.chiayi.gov.tw/News_Content.aspx?n=455&s=945868",
      "date": "2026/07/16",
      "query": "市府新聞"
    },
    {
      "headline": "兄弟抵嘉詐騙OUT嘉市警方與中信兄弟攜手反詐",
      "source": "嘉義市政府/警察局",
      "link": "https://www.chiayi.gov.tw/News_Content.aspx?n=455&s=945979",
      "date": "2026/07/15",
      "query": "市府新聞"
    },
    {
      "headline": "嘉義市勇奪2026IASE非六都最高榮譽「城市影響力治理獎」以人為本打造影響力城市",
      "source": "嘉義市政府/企劃處/觀光新聞處",
      "link": "https://www.chiayi.gov.tw/News_Content.aspx?n=455&s=945939",
      "date": "2026/07/15",
      "query": "市府新聞"
    },
    {
      "headline": "嘉市警推出沉浸式防詐遊戲榮獲IASE首獎肯定",
      "source": "嘉義市政府/警察局",
      "link": "https://www.chiayi.gov.tw/News_Content.aspx?n=455&s=945920",
      "date": "2026/07/15",
      "query": "市府新聞"
    },
    {
      "headline": "支持藝文不間斷！黃敏惠市長出席「財神盃」頒獎典禮驚喜抱回「市長全勤獎」",
      "source": "嘉義市政府/教育處/觀光新聞處",
      "link": "https://www.chiayi.gov.tw/News_Content.aspx?n=455&s=945909",
      "date": "2026/07/15",
      "query": "市府新聞"
    },
    {
      "headline": "嘉邑三賢宮、嘉邑慈音堂、嘉邑振武堂、鎮安宮池府千歲平安遶境祈福活動將登場！交管資訊公開",
      "source": "嘉義市政府/警察局/觀光新聞處",
      "link": "https://www.chiayi.gov.tw/News_Content.aspx?n=455&s=945907",
      "date": "2026/07/15",
      "query": "市府新聞"
    },
    {
      "headline": "嘉義市科學168教育博覽會將登場！交管資訊公開",
      "source": "嘉義市政府/警察局/觀光新聞處",
      "link": "https://www.chiayi.gov.tw/News_Content.aspx?n=455&s=945894",
      "date": "2026/07/15",
      "query": "市府新聞"
    },
    {
      "headline": "黃敏惠市長開球點燃戰火！中信兄弟、味全龍決戰棒球原鄉",
      "source": "嘉義市政府/教育處/觀光新聞處",
      "link": "https://www.chiayi.gov.tw/News_Content.aspx?n=455&s=945789",
      "date": "2026/07/14",
      "query": "市府新聞"
    },
    {
      "headline": "博愛陸橋配合鐵高施工0720至0723、0727至0728(夜間21時至翌日6時)全線封閉",
      "source": "嘉義市政府/交通處/觀光新聞處",
      "link": "https://www.chiayi.gov.tw/News_Content.aspx?n=455&s=945756",
      "date": "2026/07/14",
      "query": "市府新聞"
    }
  ],
  "complaint_stats": {
    "total": 78793,
    "record_count": 535,
    "category_counts": {
      "公共安全": 37949,
      "交通停車": 7743,
      "道路路平": 280,
      "環境衛生": 5,
      "行政服務": 6
    },
    "subcategory_counts": {
      "公共安全": {
        "交通事故": 37891,
        "路燈照明": 20,
        "水域安全": 38
      },
      "交通停車": {
        "交通事故": 7705,
        "公有停車場": 38
      },
      "道路路平": {
        "電力管線": 43,
        "電信管線": 18,
        "自來水管線": 35,
        "市府工程": 12,
        "橋梁設施": 172
      },
      "環境衛生": {
        "噪音管制": 5
      },
      "行政服務": {
        "陳情管道": 6
      }
    },
    "top_roads": [
      {
        "road": "東區嘉義",
        "count": 18
      },
      {
        "road": "蘭潭水庫",
        "count": 12
      },
      {
        "road": "西區劉厝村里大富路",
        "count": 3
      },
      {
        "road": "西區湖內村里健康十街",
        "count": 2
      },
      {
        "road": "西區保安村里友孝路3",
        "count": 2
      },
      {
        "road": "西區光路村里南京東街",
        "count": 2
      },
      {
        "road": "西區車店村里新建街9",
        "count": 2
      },
      {
        "road": "西區新富村里民生北路",
        "count": 2
      },
      {
        "road": "東區中山村里劉厝路",
        "count": 2
      },
      {
        "road": "西區湖內村里健康二路",
        "count": 2
      }
    ],
    "top_categories": [
      {
        "category": "公共安全",
        "count": 37949
      },
      {
        "category": "交通停車",
        "count": 7743
      },
      {
        "category": "道路路平",
        "count": 280
      },
      {
        "category": "行政服務",
        "count": 6
      },
      {
        "category": "環境衛生",
        "count": 5
      }
    ],
    "year_counts": {
      "2014": 2988,
      "2015": 2986,
      "2016": 2991,
      "2017": 2990,
      "2018": 2992,
      "2019": 3007,
      "2020": 3286,
      "2021": 3035,
      "2022": 3112,
      "2023": 3319,
      "2024": 3271,
      "2025": 8890,
      "2026": 2878,
      "2012": 1,
      "2013": 1
    },
    "updated_at": "2026-07-16T13:41:36.942085",
    "source": "data.chiayi.gov.tw"
  },
  "council": {
    "meetings_count": 9,
    "councilors": [
      "傅大偉",
      "黃露慧",
      "黃盈智",
      "陳家平",
      "張敏琪",
      "郭定緯",
      "張榮藏",
      "顏田慎節",
      "戴寧",
      "李奕德",
      "陳姿妏",
      "張秀華",
      "鄭光宏",
      "黃敏修",
      "黃思婷",
      "黃大祐",
      "林煒軒",
      "蘇澤峰",
      "孫貫志",
      "蔡文旭",
      "蔡坤叡",
      "李忠曆",
      "王浩"
    ],
    "question_count": 8
  },
  "citizen_stats": {},
  "social_posts": [
    {
      "id": "ptt-httpswwwpttccbbsChiayiM1784013000A6CBhtml",
      "platform": "PTT",
      "platform_color": "#00b300",
      "board": "Chiayi",
      "date": "07/15",
      "author": "PTT 鄉民",
      "title": "[問題] 嘉義市雷射臉部肉芽的診所",
      "url": "https://www.ptt.cc/bbs/Chiayi/M.1784013000.A.6CB.html",
      "reactions": 0,
      "comments": 0,
      "category": "市政議題",
      "source": "ptt"
    },
    {
      "id": "ptt-httpswwwpttccbbsChiayiM1783945445AA6Fhtml",
      "platform": "PTT",
      "platform_color": "#00b300",
      "board": "Chiayi",
      "date": "07/13",
      "author": "PTT 鄉民",
      "title": "[揪團] 7/17週五羽球臨打團",
      "url": "https://www.ptt.cc/bbs/Chiayi/M.1783945445.A.A6F.html",
      "reactions": 0,
      "comments": 0,
      "category": "市政議題",
      "source": "ptt"
    },
    {
      "id": "ptt-httpswwwpttccbbsChiayiM1783941568AB35html",
      "platform": "PTT",
      "platform_color": "#00b300",
      "board": "Chiayi",
      "date": "07/16",
      "author": "PTT 鄉民",
      "title": "[新聞] 快新聞/切割民眾黨!美女網紅驚傳｢無黨籍參選市議員｣想借外",
      "url": "https://www.ptt.cc/bbs/Chiayi/M.1783941568.A.B35.html",
      "reactions": 0,
      "comments": 0,
      "category": "市政議題",
      "source": "ptt"
    },
    {
      "id": "ptt-httpswwwpttccbbsChiayiM1783920074A692html",
      "platform": "PTT",
      "platform_color": "#00b300",
      "board": "Chiayi",
      "date": "07/13",
      "author": "PTT 鄉民",
      "title": "[買賣] 7-11開心卡/肯德基/萬家福/統一數位禮券/SNOOPY事事如意碗組",
      "url": "https://www.ptt.cc/bbs/Chiayi/M.1783920074.A.692.html",
      "reactions": 0,
      "comments": 0,
      "category": "市政議題",
      "source": "ptt"
    },
    {
      "id": "ptt-httpswwwpttccbbsChiayiM1783783710A204html",
      "platform": "PTT",
      "platform_color": "#00b300",
      "board": "Chiayi",
      "date": "07/14",
      "author": "PTT 鄉民",
      "title": "[揪團] 嘉義資訊社群(Line社團)",
      "url": "https://www.ptt.cc/bbs/Chiayi/M.1783783710.A.204.html",
      "reactions": 0,
      "comments": 0,
      "category": "市政議題",
      "source": "ptt"
    },
    {
      "id": "ptt-httpswwwpttccbbsChiayiM1783757541A27Ahtml",
      "platform": "PTT",
      "platform_color": "#00b300",
      "board": "Chiayi",
      "date": "07/11",
      "author": "PTT 鄉民",
      "title": "[買賣] 快拆不銹鋼前置過濾器 等生活物品",
      "url": "https://www.ptt.cc/bbs/Chiayi/M.1783757541.A.27A.html",
      "reactions": 0,
      "comments": 0,
      "category": "市政議題",
      "source": "ptt"
    },
    {
      "id": "ptt-httpswwwpttccbbsChiayiM1783725220AFA1html",
      "platform": "PTT",
      "platform_color": "#00b300",
      "board": "Chiayi",
      "date": "07/11",
      "author": "PTT 鄉民",
      "title": "[買賣] 道奇球場入場禮-搖頭娃娃、球衣、冠軍戒",
      "url": "https://www.ptt.cc/bbs/Chiayi/M.1783725220.A.FA1.html",
      "reactions": 0,
      "comments": 0,
      "category": "市政議題",
      "source": "ptt"
    },
    {
      "id": "ptt-httpswwwpttccbbsChiayiM1783700278A090html",
      "platform": "PTT",
      "platform_color": "#00b300",
      "board": "Chiayi",
      "date": "07/11",
      "author": "PTT 鄉民",
      "title": "[徵求] iPhone se3 128g 黑/紅",
      "url": "https://www.ptt.cc/bbs/Chiayi/M.1783700278.A.090.html",
      "reactions": 0,
      "comments": 0,
      "category": "市政議題",
      "source": "ptt"
    },
    {
      "id": "ptt-httpswwwpttccbbsChiayiM1783697990A326html",
      "platform": "PTT",
      "platform_color": "#00b300",
      "board": "Chiayi",
      "date": "07/10",
      "author": "PTT 鄉民",
      "title": "[買賣] 西堤陶板屋 麥當勞 衛生紙 資生堂 快煮壺",
      "url": "https://www.ptt.cc/bbs/Chiayi/M.1783697990.A.326.html",
      "reactions": 0,
      "comments": 0,
      "category": "市政議題",
      "source": "ptt"
    },
    {
      "id": "ptt-httpswwwpttccbbsChiayiM1783599314AD34html",
      "platform": "PTT",
      "platform_color": "#00b300",
      "board": "Chiayi",
      "date": "07/13",
      "author": "PTT 鄉民",
      "title": "[問題] 嘉義市室內月租停車",
      "url": "https://www.ptt.cc/bbs/Chiayi/M.1783599314.A.D34.html",
      "reactions": 0,
      "comments": 0,
      "category": "交通停車",
      "source": "ptt"
    },
    {
      "id": "ptt-httpswwwpttccbbsChiayiM1783491175A6F6html",
      "platform": "PTT",
      "platform_color": "#00b300",
      "board": "Chiayi",
      "date": "07/14",
      "author": "PTT 鄉民",
      "title": "[問題] 新悅跟福容 烤鴨選哪個？",
      "url": "https://www.ptt.cc/bbs/Chiayi/M.1783491175.A.6F6.html",
      "reactions": 0,
      "comments": 0,
      "category": "市政議題",
      "source": "ptt"
    },
    {
      "id": "ptt-httpswwwpttccbbsChiayiM1783482871AECFhtml",
      "platform": "PTT",
      "platform_color": "#00b300",
      "board": "Chiayi",
      "date": "07/10",
      "author": "PTT 鄉民",
      "title": "[問題] 尋找短租房源（1個月）",
      "url": "https://www.ptt.cc/bbs/Chiayi/M.1783482871.A.ECF.html",
      "reactions": 0,
      "comments": 0,
      "category": "市政議題",
      "source": "ptt"
    }
  ]
}