[
  {
    "id": "ptt-bbsGossipingM1780502148A0E4html",
    "platform": "PTT",
    "platform_color": "#00b300",
    "board": "Gossiping",
    "date": "6/03",
    "author": "PTT 鄉民",
    "title": "[新聞] 黃敏惠蟬聯「五星市長」 感謝嘉義市民肯",
    "url": "https://www.ptt.cc/bbs/Gossiping/M.1780502148.A.0E4.html",
    "reactions": 1,
    "comments": 0,
    "category": "市政議題",
    "source": "ptt"
  },
  {
    "id": "ptt-bbsGossipingM1780361959A51Fhtml",
    "platform": "PTT",
    "platform_color": "#00b300",
    "board": "Gossiping",
    "date": "6/02",
    "author": "PTT 鄉民",
    "title": "Re: [新聞] 不忍了！嘉義市5毒駕「姓名、照片」",
    "url": "https://www.ptt.cc/bbs/Gossiping/M.1780361959.A.51F.html",
    "reactions": 2,
    "comments": 0,
    "category": "市政議題",
    "source": "ptt"
  },
  {
    "id": "ptt-bbsGossipingM1780355389A98Fhtml",
    "platform": "PTT",
    "platform_color": "#00b300",
    "board": "Gossiping",
    "date": "6/02",
    "author": "PTT 鄉民",
    "title": "[新聞] 不忍了！嘉義市5毒駕「姓名、照片」全公",
    "url": "https://www.ptt.cc/bbs/Gossiping/M.1780355389.A.98F.html",
    "reactions": 37,
    "comments": 0,
    "category": "市政議題",
    "source": "ptt"
  },
  {
    "id": "ptt-bbsGossipingM1778584660A40Fhtml",
    "platform": "PTT",
    "platform_color": "#00b300",
    "board": "Gossiping",
    "date": "5/12",
    "author": "PTT 鄉民",
    "title": "[新聞] 現勘未受邀嘉義市府批「割稻仔尾」 王美",
    "url": "https://www.ptt.cc/bbs/Gossiping/M.1778584660.A.40F.html",
    "reactions": 2,
    "comments": 0,
    "category": "市政議題",
    "source": "ptt"
  },
  {
    "id": "ptt-bbsGossipingM1778161410A497html",
    "platform": "PTT",
    "platform_color": "#00b300",
    "board": "Gossiping",
    "date": "5/07",
    "author": "PTT 鄉民",
    "title": "[新聞] 嘉義市人氣柯爾鴨遭竊 竊賊對鏡頭比YA超",
    "url": "https://www.ptt.cc/bbs/Gossiping/M.1778161410.A.497.html",
    "reactions": 4,
    "comments": 0,
    "category": "市政議題",
    "source": "ptt"
  },
  {
    "id": "ptt-bbsGossipingM1777891219A42Ahtml",
    "platform": "PTT",
    "platform_color": "#00b300",
    "board": "Gossiping",
    "date": "5/04",
    "author": "PTT 鄉民",
    "title": "Re: [問卦] 嘉義市才是民主典範啊 政黑好像很氣？",
    "url": "https://www.ptt.cc/bbs/Gossiping/M.1777891219.A.42A.html",
    "reactions": 0,
    "comments": 0,
    "category": "市政議題",
    "source": "ptt"
  },
  {
    "id": "ptt-bbsChiayiM1782713150AF48html",
    "platform": "PTT",
    "platform_color": "#00b300",
    "board": "Chiayi",
    "date": "6/29",
    "author": "PTT 鄉民",
    "title": "Fw: [情報] 6月29日起 嘉義縣YouBike新增13個站點",
    "url": "https://www.ptt.cc/bbs/Chiayi/M.1782713150.A.F48.html",
    "reactions": 0,
    "comments": 0,
    "category": "市政議題",
    "source": "ptt"
  },
  {
    "id": "ptt-bbsChiayiM1781442444AF07html",
    "platform": "PTT",
    "platform_color": "#00b300",
    "board": "Chiayi",
    "date": "6/14",
    "author": "PTT 鄉民",
    "title": "[問題] BRT嘉義公園出發",
    "url": "https://www.ptt.cc/bbs/Chiayi/M.1781442444.A.F07.html",
    "reactions": 3,
    "comments": 0,
    "category": "公園綠地",
    "source": "ptt"
  },
  {
    "id": "ptt-bbsChiayiM1781026168A128html",
    "platform": "PTT",
    "platform_color": "#00b300",
    "board": "Chiayi",
    "date": "6/10",
    "author": "PTT 鄉民",
    "title": "［新聞］ 嘉義市議員王浩指快慢車道分隔島易成",
    "url": "https://www.ptt.cc/bbs/Chiayi/M.1781026168.A.128.html",
    "reactions": 35,
    "comments": 0,
    "category": "市政議題",
    "source": "ptt"
  },
  {
    "id": "ptt-bbsChiayiM1780912521AA17html",
    "platform": "PTT",
    "platform_color": "#00b300",
    "board": "Chiayi",
    "date": "6/08",
    "author": "PTT 鄉民",
    "title": "[問題] 嘉義便宜全車烤漆",
    "url": "https://www.ptt.cc/bbs/Chiayi/M.1780912521.A.A17.html",
    "reactions": 1,
    "comments": 0,
    "category": "市政議題",
    "source": "ptt"
  },
  {
    "id": "ptt-bbsChiayiM1780900878A371html",
    "platform": "PTT",
    "platform_color": "#00b300",
    "board": "Chiayi",
    "date": "6/08",
    "author": "PTT 鄉民",
    "title": "[新聞] 嘉義藍白合2／張啟楷拋「0歲存5萬」",
    "url": "https://www.ptt.cc/bbs/Chiayi/M.1780900878.A.371.html",
    "reactions": 1,
    "comments": 0,
    "category": "市政議題",
    "source": "ptt"
  },
  {
    "id": "ptt-bbsChiayiM1780787717AFADhtml",
    "platform": "PTT",
    "platform_color": "#00b300",
    "board": "Chiayi",
    "date": "6/07",
    "author": "PTT 鄉民",
    "title": "[新聞] 嘉義8旬身障嬤日行10里撿千瓶菸蒂 兌換2",
    "url": "https://www.ptt.cc/bbs/Chiayi/M.1780787717.A.FAD.html",
    "reactions": 9,
    "comments": 0,
    "category": "社福高齡",
    "source": "ptt"
  }
]